<?xml version="1.0" encoding="UTF-8"?>
<!-- Created with TexturePacker http://www.codeandweb.com/texturepacker-->
<!-- $TexturePacker:SmartUpdate:9f7167af7921cef1eef9eff1612501e8:27de700dc370cbd6ca47e38fd8d897d1:658438ba26ba75100890aef339493130$ -->
<!--Format:
n  => name of the sprite
x  => sprite x pos in texture
y  => sprite y pos in texture
w  => sprite width (may be trimmed)
h  => sprite height (may be trimmed)
pX => x pos of the pivot point (relative to sprite width)
pY => y pos of the pivot point (relative to sprite height)
oX => sprite's x-corner offset (only available if trimmed)
oY => sprite's y-corner offset (only available if trimmed)
oW => sprite's original width (only available if trimmed)
oH => sprite's original height (only available if trimmed)
r => 'y' only set if sprite is rotated
with polygon mode enabled:
vertices   => points in sprite coordinate system (x0,y0,x1,y1,x2,y2, ...)
verticesUV => points in sheet coordinate system (x0,y0,x1,y1,x2,y2, ...)
triangles  => sprite triangulation, 3 vertex indices per triangle
-->
<TextureAtlas imagePath="gfx/island_overlay/island02_sheet02.png" width="1024" height="1024">
    <sprite n="eye_glow" x="439" y="2" w="410" h="406" pX="0.5" pY="0.5" r="y"/>
    <sprite n="eye_ring" x="2" y="2" w="435" h="365" pX="0.5" pY="0.5" oX="0" oY="21" oW="435" oH="408"/>
    <sprite n="eye_ring_highlight" x="404" y="410" w="283" h="300" pX="0.5" pY="0.5" oX="0" oY="1" oW="300" oH="285" r="y"/>
    <sprite n="eye_shadow" x="424" y="712" w="297" h="297" pX="0.5" pY="0.5" oX="0" oY="0" oW="298" oH="298"/>
    <sprite n="eyelid_bottom" x="723" y="410" w="265" h="105" pX="0.5" pY="0.5"/>
    <sprite n="eyelid_bottom_edge" x="2" y="770" w="78" h="252" pX="0.5" pY="0.5" r="y"/>
    <sprite n="eyelid_bottom_edge_highlight" x="82" y="770" w="69" h="251" pX="0.5" pY="0.5" r="y"/>
    <sprite n="eyelid_glow_solid" x="851" y="2" w="123" h="287" pX="0.5" pY="0.5" oX="0" oY="0" oW="288" oH="124" r="y"/>
    <sprite n="eyelid_top" x="153" y="770" w="269" h="189" pX="0.5" pY="0.5" oX="0" oY="0" oW="281" oH="189"/>
    <sprite n="eyelid_top_edge" x="723" y="517" w="261" h="100" pX="0.5" pY="0.5" oX="4" oY="0" oW="265" oH="100"/>
    <sprite n="eyelid_top_edge_highlight" x="689" y="619" w="258" h="76" pX="0.5" pY="0.5"/>
    <sprite n="pupil" x="2" y="369" w="400" h="399" pX="0.5" pY="0.5" oX="0" oY="0" oW="400" oH="400"/>
</TextureAtlas>
